{
  "id": "lei-jun",
  "name": "雷军",
  "summary": "雷军是小米创始人，也是颖响力新能源汽车批评线索里最重要的创始人符号之一。",
  "description": "在这些节目里，雷军主要被提及于：EP013 中节目借小米汽车事故频发讨论创始人品牌、性能叙事与安全边界之间的错位；EP041 中节目把杂粮汽车的设计借鉴与速成逻辑，放到创始人主导的产品哲学里理解；EP062 中节目借“丐帮帮主”隐喻讨论雷军如何在粉丝政治和全球市场之间重新排序安全标准。",
  "episodes": [
    {
      "id": "EP013",
      "note": "节目借小米汽车事故频发讨论创始人品牌、性能叙事与安全边界之间的错位。"
    },
    {
      "id": "EP041",
      "note": "节目把杂粮汽车的设计借鉴与速成逻辑，放到创始人主导的产品哲学里理解。"
    },
    {
      "id": "EP062",
      "note": "节目借“丐帮帮主”隐喻讨论雷军如何在粉丝政治和全球市场之间重新排序安全标准。"
    }
  ]
}
