{
  "id": "EP053",
  "title": "南京博物院事件五点深度思考，仇英《江南春》暴露了掠夺的真相。｜产权｜掠夺｜文革｜故宫南迁文物｜徐湖平｜",
  "summary": "本期借南京博物院与《江南春》争议，追问博物馆在接收私人捐赠后到底有没有任意处置权，并把文物调剂、产权失序与近现代文化掠夺放回同一条历史链条里理解。",
  "tags": [
    "产权",
    "掠夺",
    "文革",
    "故宫南迁文物",
    "徐湖平",
    "博物馆伦理"
  ],
  "people": [
    "庞增和",
    "徐湖平"
  ],
  "themes": [
    "产权失序与文化掠夺"
  ],
  "concepts": [
    "cultural-plunder"
  ],
  "models": [
    "principal-agent"
  ],
  "relatedEpisodes": [
    "EP092",
    "EP116"
  ],
  "topic": {
    "background": "节目并不把焦点放在《江南春》是真是假，而是把争议转向更根本的问题：一个接受私人捐赠、承担公共托管职责的机构，是否可以绕过原家族与公众监督，自行决定一件文化资产的去留与处置。",
    "conflicts": [
      "博物馆作为公共托管者，究竟有没有权力把捐赠物当成完全属于自己的资产来处理。",
      "文物保护与产权边界之间，机构到底应守住怎样的底线。",
      "近现代把私产不断转化成公产的历史，究竟是在保护文明，还是在抽干文明赖以生长的私人土壤。"
    ],
    "boundaries": [
      "这期不试图完成古画真伪鉴定，真假并不是节目最想追问的问题。",
      "重点不在南京博物院这一家机构的运营细节，而在托管伦理和产权秩序本身。",
      "节目借个案讨论更长的历史链条，不把问题缩减成一场单纯的舆论事件。"
    ],
    "mechanism": "历史压力下的私产外移 -> 文化资产被公共机构接管 -> 机构逐渐把托管权误当所有权 -> 原家族与公众知情权被排除 -> 文物事件暴露出更深的产权失序与文明断裂。",
    "extensions": [
      "这一期适合与文物南迁、文革抄家和私人收藏史一起看，能更清楚地理解文化资产是如何失去原生土壤的。",
      "也可以追问：一个公共机构如果不受捐赠伦理和透明程序约束，它和普通强势占有者的区别到底在哪。",
      "节目把“取信于人”视作核心问题，意味着文化保护最终还是要回到信任与边界。",
      "对于今天的文化机构治理来说，程序正义本身就是合法性的一部分。"
    ]
  },
  "viewpoints": [
    {
      "title": "真假不是最重要的，底线才是",
      "body": "节目认为，就算《江南春》最后被证实为伪作，也不改变背后的程序问题。一个博物馆至少应当公开、通知原家族或说明处置依据，而不是把托管权直接变成任意处置权。"
    },
    {
      "title": "私人文化资产变成公产，并不天然意味着文明被更好地保存",
      "body": "视频把庞家捐赠放回时代背景里理解，强调许多“主动捐赠”背后未必真的存在完整自由意志。私产变公产的过程，本身就可能伴随对文化生活方式的整体剥离。"
    },
    {
      "title": "文化损失不只发生在文物被毁时，也发生在原生语境被切断时",
      "body": "节目最在意的不是画是不是还在，而是原有家族、空间和生活方式已经被整套拔走。文物没有彻底消失，不等于文明没有遭遇掠夺。"
    },
    {
      "title": "公共机构一旦失去取信于人的能力，专业性也会跟着贬值",
      "body": "节目对机构最严厉的批评，不是它做错了一件事，而是它在面对后人时长期回避、缺乏解释。这会让博物馆从文化托管者滑向权力占有者。"
    }
  ],
  "extensions": [
    "这一期适合放在“产权与文明”主题下反复回看，因为它讨论的不是一幅画，而是文化如何失去民间根系。",
    "如果继续追问，会自然走到私产、公产与公共信任之间到底如何重新划边界的问题。",
    "节目也提醒人们，不要把所有文化保护都简单等同于国家接管。",
    "看懂这期之后，再看很多关于文物、家族史和记忆政治的争论，会更容易抓到底层逻辑。"
  ]
}
