{
  "id": "EP121",
  "title": "潘石屹，脱离时间去看事件，你根本看不懂他30年的所有选择，和背后极致前瞻性",
  "summary": "本期主张把潘石屹的婚姻、上市、家族信托、卖楼和退出动作全部放回各自的时间窗口里看，而不是用事后阴谋论把三十年的决策压成一个故事。节目核心判断是：潘石屹和张欣真正稀缺的，不是算无遗策，而是更早完成了对资产、法域和退出节奏的前瞻布局。",
  "tags": [
    "潘石屹",
    "张欣",
    "SOHO中国",
    "家族信托",
    "时间维度",
    "前瞻性",
    "抑制贪婪",
    "资产保全"
  ],
  "people": [
    "潘石屹",
    "张欣",
    "王石"
  ],
  "themes": [
    "时间尺度与资产前瞻",
    "家族信托与资产保全"
  ],
  "concepts": [
    "time-window-reading"
  ],
  "models": [
    "asset-preservation-architecture",
    "institutional-fit"
  ],
  "relatedEpisodes": [
    "EP010",
    "EP012",
    "EP078"
  ],
  "topic": {
    "background": "节目一开始就反对把潘石屹理解成一个从二十多岁起就写好全部阴谋脚本的人。主持人的框架是：商业人物的许多关键动作必须放在时代窗口里看，包括他如何赚到第一桶金、为什么和张欣结合、为何去香港上市、为什么做离岸信托、又为什么在后期逐步卖楼和退出。",
    "conflicts": [
      "潘石屹的很多动作，到底是长期阴谋，还是在不同时间窗口里做出的前瞻判断。",
      "婚姻、上市、信托和卖楼，是偶然拼在一起的选择，还是一套互相咬合的资产保全架构。",
      "企业家最难的，不是抓到每一个上升机会，而是知道什么时候该抑制贪婪和先退一步。",
      "评价商业人物时，到底该按结果做道德标签，还是按时代位置和核心诉求去理解。"
    ],
    "boundaries": [
      "这期重点是时间感和前瞻性，不是为潘石屹做人物洗白。",
      "节目并不否认个人选择有利己面向，但强调不能脱离时代窗口去强行拼出线性阴谋论。",
      "讨论的核心是财富与退出策略，不是对整个房地产史做全面回顾。"
    ],
    "mechanism": "在特定时代窗口获得第一桶金和城市机会 -> 与张欣形成本土开发判断和全球资本结构能力的互补 -> 通过香港上市、离岸主体和家族信托把资产提前装入更适配的架构 -> 在周期变化前持续卖楼、减轻暴露并逐步退出 -> 遇到交易受阻时继续止贪而不是硬顶 -> 最终留下更多人生空间与资产安全边界。",
    "extensions": [
      "为什么很多后来被解读成阴谋的动作，放回原来的时间点看，其实更像模糊但有效的前瞻判断。",
      "家族信托和离岸主体真正有用时，从来不是临时抱佛脚，而是和婚姻、上市、退出节奏一起提前完成。",
      "企业家最难做到的，也许不是看见机会，而是在还能继续赚时先学会止贪。",
      "判断一个商业人物，最应该看的不是他后来被讲成什么故事，而是他在关键节点守住了什么核心诉求。"
    ]
  },
  "viewpoints": [
    {
      "title": "脱离时间谈潘石屹，只会把前瞻判断误读成长期阴谋",
      "body": "节目反复提醒，很多人喜欢站在结果倒推，把潘石屹早年的婚姻、海南经历和后来信托安排串成一条阴谋线。但主持人的意思是，商业人物在当下看到的是模糊概率，不是已经写好的剧本。"
    },
    {
      "title": "第一桶金和后续跃迁，都离不开特定时代窗口",
      "body": "节目讲陈女士、海南热和早年北京俱乐部时，真正要说明的是同一个道理：同样的人、同样的能力，如果换一个时间点，未必还能拿到同样结果。潘石屹能上桌，本身就是时代窗口的一部分。"
    },
    {
      "title": "张欣与潘石屹的结合，是能力互补而不是简单婚姻跳板",
      "body": "主持人把两人的组合看成一种非常清晰的互补关系：潘石屹懂本土土地和产品，张欣懂全球资本、离岸架构和金融逻辑。也正因为如此，后来的上市、信托和资产安排在节目里看起来并不神秘。"
    },
    {
      "title": "家族信托、香港上市与卖楼撤退，是一套前置保全动作",
      "body": "这期最核心的判断之一，是把潘石屹后来的财富安排理解成完整链条而不是孤立动作。信托不是凭空冒出来的安全壳，而是和上市地点、资产出售顺序、资金外移节奏一起构成了保护力。"
    },
    {
      "title": "真正稀缺的不是算无遗策，而是知道什么时候止贪",
      "body": "节目在结尾反复强调“抑制贪婪”。主持人的意思是，很多人不是没看到风险，而是在还能继续赚的时候不肯停；潘石屹相对特别之处，不在于完全无错，而在于更早接受了该退的时候要退。"
    },
    {
      "title": "商业人物更适合按时代与核心诉求理解，而不是按神话或罪人两极裁决",
      "body": "这期最后把话题拉回更普遍的方法论。无论潘石屹、王石还是其他人物，都不适合被压成单一神话或单一道德标签；更有解释力的方式，是看他们在各自时代里到底守住了什么。"
    }
  ],
  "extensions": [
    "这期和 EP010 对照阅读尤其有价值，一集讲工具为什么会被穿透，一集讲什么叫在风暴前把架构先搭好。",
    "它也和万科几集形成侧面对照，因为潘石屹、王石和万科管理层在退出、交棒和止贪节奏上的差异非常鲜明。",
    "节目提供的不只是人物判断，更是一种看商业决策的方法：先问时间窗口，再问结构，最后才问道德标签。",
    "对于任何关心财富保全的人，这期最大的启发可能不是复制谁的路径，而是理解“前置完成”为什么比“事后补救”重要得多。",
    "在知识库里，这一集适合作为连接房地产人物、家族信托和时间尺度思维的入口条目。"
  ],
  "videoLinks": [
    {
      "platform": "bilibili",
      "status": "unavailable",
      "note": "已下架"
    },
    {
      "platform": "youtube",
      "url": "https://www.youtube.com/watch?v=SIj7VTRSvc4"
    }
  ]
}
