{
  "id": "gray-oil-network",
  "name": "灰色石油网络",
  "summary": "绕开正规结算和监管的石油流动，会在影子体系中重塑货币、制裁和地缘利益。",
  "definition": "灰色石油网络指通过影子船队、转口贸易、非正规结算和中间商结构完成的能源交易。它不是普通走私概念，而是地缘压力下绕开美元、海关统计和制裁体系的替代通道。它成立的原因在于，能源刚需不会因制裁消失，只会寻找更隐蔽、更高成本的流动方式。",
  "importance": "这个概念重要，是因为它把石油美元问题从公开贸易表面推进到影子结算层。真正影响霸权和制裁效果的，常常是那些账面之外的通道。",
  "episodes": [
    {
      "id": "EP107",
      "note": "节目认为灰色石油才是石油美元真正的漏洞，也是川普战略的真正打击对象。"
    }
  ],
  "signals": [
    "贸易路径复杂，真实买卖双方被中间层遮蔽。",
    "结算方式绕开主要金融体系。",
    "制裁后能源仍以更高成本流动。",
    "大国开始针对通道、船队和保险下手。"
  ],
  "boundaries": [
    "它不能把所有非西方能源贸易都视为灰色。",
    "它不适合忽略合法贸易和国家间正常折扣交易。",
    "灰色网络有成本和失控风险，不是稳定替代体系。"
  ],
  "questions": [
    "石油流动绕开了哪些公开规则？",
    "谁从灰色通道中获益？",
    "打击网络会强化还是削弱美元秩序？",
    "影子成本最终由谁承担？"
  ],
  "context": "特朗普石油美元棋局相关节目把灰色石油视为美元体系漏洞。打击对象不只是某个产油国，而是绕开公开秩序的结算网络和通道控制。",
  "episodeHighlights": [
    {
      "id": "EP107",
      "title": "未来12个月美元黄金怎么走？看懂川普的石油美元棋局，你就全明白了",
      "note": "节目认为灰色石油才是石油美元真正的漏洞，也是川普战略的真正打击对象。",
      "summary": "本期围绕美元、黄金与石油美元体系，提出一个强判断：真正侵蚀美元霸权的不是公开数据里的去美元化，而是藏在统计之外的灰色石油网络；特朗普真正想做的，也不是战略收缩，而是用代理围堵重新堵上这个漏洞。",
      "mechanism": "灰色石油网络长期绕开美元结算 -> 各国对美元的刚性需求被慢慢掏空 -> 特朗普通过阵营切割、盟友分担与区域封堵压缩灰色贸易通道 -> 石油与美元重新绑定得更紧 -> 若该战略成立，美元需求增强而黄金承压。"
    }
  ],
  "relatedConcepts": [],
  "relatedModels": [
    "proxy-containment-ring"
  ],
  "relatedThemes": [
    "美元体系与灰色贸易"
  ],
  "relatedPeople": [
    "特朗普"
  ]
}
