{
  "id": "route-substitution-illusion",
  "name": "航线替代幻觉",
  "summary": "新的港口、陆路或航线可以分流局部业务，但很难在短期内替代真正的世界级主通道。",
  "definition": "航线替代幻觉指的是把局部补充、拼货节点或新兴路线误读成主航道替代者。它忽略了吞吐量、配套设施、法律信用、历史积累和位置稀缺性之间的巨大差距，容易把补充路径夸大成结构性颠覆。",
  "importance": "这个概念适合整理海南封关、新疆陆运和北冰洋航线等议题，因为这些讨论都容易滑向“新路线马上取代旧秩序”的想象。",
  "episodes": [
    {
      "id": "EP051",
      "note": "节目反复强调，海南最多承接部分拼货与免税消费，不可能整体替代新加坡。"
    },
    {
      "id": "EP073",
      "note": "节目把“新加坡货运暴跌”和“海洋时代回到陆地时代”的说法直接视为夸大叙事。"
    },
    {
      "id": "EP077",
      "note": "节目认为北冰洋航线即便有潜力，也仍受格陵兰命门和美国介入限制。"
    }
  ]
}
